buildbot_sitenav/VERSION
buildbot_sitenav/__init__.py
buildbot_sitenav/static/scripts.js
buildbot_sitenav/static/styles.css
buildbot_sitenav-0.1.0.dist-info/METADATA
buildbot_sitenav-0.1.0.dist-info/WHEEL
buildbot_sitenav-0.1.0.dist-info/entry_points.txt
buildbot_sitenav-0.1.0.dist-info/top_level.txt
buildbot_sitenav-0.1.0.dist-info/RECORD
