Metadata-Version: 2.1
Name: buildbot-sitenav
Version: 0.1.0
Summary: Buildbot site navigation plugin
Home-page: https://github.com/cheshirekow/buildbot_sitenav
Author: Josh Bialkowski
Author-email: josh.bialkowski@gmail.com
License: GNU GPL
Download-URL: https://github.com/cheshirekow/buildbot_sitenav/archive/0.1.0.tar.gz
Platform: UNKNOWN
